refactor_llm_analyzer/__init__.py
refactor_llm_analyzer/main.py
refactor_llm_analyzer/prompts.py
refactor_llm_analyzer-2025.12.21134750.dist-info/METADATA
refactor_llm_analyzer-2025.12.21134750.dist-info/WHEEL
refactor_llm_analyzer-2025.12.21134750.dist-info/top_level.txt
refactor_llm_analyzer-2025.12.21134750.dist-info/RECORD
