Metadata-Version: 2.4
Name: refactor-llm-analyzer
Version: 2025.12.21134750
Summary: A new package designed to facilitate structured and reliable analysis of user input related to software refactoring in the context of LLM capabilities. It accepts a user's discussion or question about
Author-email: refactor-llm-analyzer <hi@eugene.plus>
License: MIT
Project-URL: Homepage, https://github.com/chigwell/refactor-llm-analyzer
Requires-Python: >=3.9
Requires-Dist: langchain-llm7>=0.0.0
Requires-Dist: llmatch-messages>=0.0.0
Requires-Dist: langchain-core>=0.3.0
